CHANGELOG.md
CONTRIBUTING.md
LICENSE
MANIFEST.in
README.md
pyproject.toml
setup.py
.github/CODE_OF_CONDUCT.md
.github/PULL_REQUEST_TEMPLATE.md
tests/wireguard_test.py
wireguard_py/__init__.py
wireguard_py/wgpy.py
wireguard_py/wireguard_common.py
wireguard_py/wireguard_py.c
wireguard_py/wireguard_py.pxd
wireguard_py/wireguard_py.pyi
wireguard_py/wireguard_py.pyx
wireguard_py.egg-info/PKG-INFO
wireguard_py.egg-info/SOURCES.txt
wireguard_py.egg-info/dependency_links.txt
wireguard_py.egg-info/entry_points.txt
wireguard_py.egg-info/requires.txt
wireguard_py.egg-info/top_level.txt
wireguard_py/wireguard_tools/wireguard.c
wireguard_py/wireguard_tools/wireguard.h