Metadata-Version: 2.1
Name: wireguard-py
Version: 2023.6.12
Summary: Cython library to manage Wireguard configuration
Author-email: Eric Schwimmer <schwim@meta.com>, Richard Ross <richardross@meta.com>
Project-URL: Homepage, https://github.com/facebookincubator/wireguard_py
Project-URL: Bug Tracker, https://github.com/facebookincubator/wireguard_py/issues
Classifier: Development Status :: 5 - Production/Stable
Classifier: Environment :: Console
Classifier: Environment :: No Input/Output (Daemon)
Classifier: Intended Audience :: Developers
Classifier: Intended Audience :: System Administrators
Classifier: License :: OSI Approved :: MIT License
Classifier: Programming Language :: Python
Classifier: Programming Language :: Python :: 3
Requires-Python: >=3
License-File: LICENSE
